yzconfig/__init__.py
yzconfig/yzconfig.py
yzconfig/tests/__init__.py
yzconfig/tests/test_yzconfig.py
yzconfig-1.0.dist-info/DESCRIPTION.rst
yzconfig-1.0.dist-info/METADATA
yzconfig-1.0.dist-info/RECORD
yzconfig-1.0.dist-info/WHEEL
yzconfig-1.0.dist-info/metadata.json
yzconfig-1.0.dist-info/top_level.txt
