Metadata-Version: 2.0
Name: yzconfig
Version: 1.0
Summary: Easy configuration for your project
Home-page: https://github.com/ykshatroff/yzconfig
Author: Yuriy Shatrov
Author-email: ykshatrov@ya.ru
License: Apache Software License
Keywords: config settings
Platform: UNKNOWN
Classifier: Intended Audience :: Developers
Classifier: License :: OSI Approved :: Apache Software License
Classifier: Programming Language :: Python :: 2
Classifier: Programming Language :: Python :: 2.7
Classifier: Programming Language :: Python :: 3
Classifier: Programming Language :: Python :: 3.5
Classifier: Programming Language :: Python :: 3.6
Provides-Extra: dev
Requires-Dist: check-manifest; extra == 'dev'
Provides-Extra: test
Requires-Dist: coverage; extra == 'test'
